owlml/__init__.py
owlml/__main__.py
owlml/annotations.py
owlml/api.py
owlml/auth.py
owlml/dataset_versions.py
owlml/datasets.py
owlml/experiments.py
owlml/images.py
owlml/utils.py
owlml-0.2.0.dist-info/LICENSE
owlml-0.2.0.dist-info/METADATA
owlml-0.2.0.dist-info/WHEEL
owlml-0.2.0.dist-info/entry_points.txt
owlml-0.2.0.dist-info/top_level.txt
owlml-0.2.0.dist-info/RECORD
