Metadata-Version: 2.1
Name: owlml
Version: 0.2.0
Author: Sparrow Computing
Author-email: ben@sparrow.dev
License-File: LICENSE
Requires-Dist: fire
Requires-Dist: pillow
Requires-Dist: pyfarmhash
Requires-Dist: requests
Requires-Dist: tqdm
Provides-Extra: dev
Requires-Dist: black ; extra == 'dev'
Requires-Dist: isort ; extra == 'dev'
Requires-Dist: jupyter ; extra == 'dev'
Requires-Dist: pydocstyle ; extra == 'dev'
Requires-Dist: pylint ; extra == 'dev'
Requires-Dist: pytest ; extra == 'dev'
Requires-Dist: pytest-cov ; extra == 'dev'
